README.md
setup.py
scflog/cmds.py
scflog/logging_mid.py
scflog/logs_mid.py
scflog.egg-info/PKG-INFO
scflog.egg-info/SOURCES.txt
scflog.egg-info/dependency_links.txt
scflog.egg-info/entry_points.txt
scflog.egg-info/requires.txt
scflog.egg-info/top_level.txt
scflog.egg-info/zip-safe